{"_ts":[1479127365,1479127396],"_r":{"breakdown":{"html":{"bytes":[4776,4797],"requests":[1,1]},"js":{"bytes":[60202,60202],"requests":[2,2]},"css":{"bytes":[1600,1600],"requests":[2,2]},"image":{"bytes":[5402,5402],"requests":[1,1]},"flash":{"bytes":[0,0],"requests":[0,0]},"font":{"bytes":[48421,48422],"requests":[3,3]},"other":{"bytes":[0,0],"requests":[0,0]}},"date":[1479127365,1479127396],"domElements":[64,64],"domInteractive":[1107.4,752],"firstPaint":[2008.6,1614.8],"fullyLoaded":[3152,2509],"id":["161114_0D_M84","161114_J2_M88"],"loadTime":[2485,2070.2],"render":[2127,1743.6],"SpeedIndex":[2149.2,1761],"TTFB":[1009.6,652.6],"videoFrames":[[{"_t":0,"_vc":0},{"_t":2400,"_vc":95},{"_t":3700,"_vc":100}],[{"_t":0,"_vc":0},{"_t":1400,"_vc":95},{"_t":2000,"_vc":99},{"_t":2200,"_vc":100}]],"visualComplete":[2683.8,2222.6]}}